kwsbp/__init__.py
kwsbp-0.1.0.dist-info/METADATA
kwsbp-0.1.0.dist-info/WHEEL
kwsbp-0.1.0.dist-info/top_level.txt
kwsbp-0.1.0.dist-info/RECORD
